dblapi/__init__.py
dblapi/caching.py
dblapi/client.py
dblapi/data_objects.py
dblapi/errors.py
dblapi/helpers.py
dblapi/request_lib.py
dblapi/router.py
dblapi-0.1.4b0.dist-info/DESCRIPTION.rst
dblapi-0.1.4b0.dist-info/METADATA
dblapi-0.1.4b0.dist-info/RECORD
dblapi-0.1.4b0.dist-info/WHEEL
dblapi-0.1.4b0.dist-info/metadata.json
dblapi-0.1.4b0.dist-info/top_level.txt
