Metadata-Version: 2.0
Name: dblapi
Version: 0.1.4b0
Summary: Discord Bot List API Wrapper, customised for use in discord.py
Home-page: https://github.com/AndyTempel/dblapi
Author: AndyTempel
Author-email: andraz@korenc.eu
License: UNKNOWN
Download-URL: https://github.com/AndyTempel/dblapi/archive/0.1.4b.tar.gz
Keywords: dblapi,dbl
Platform: UNKNOWN
Classifier: Development Status :: 4 - Beta
Classifier: License :: OSI Approved :: MIT License
Classifier: Intended Audience :: Developers
Classifier: Natural Language :: English
Classifier: Operating System :: OS Independent
Classifier: Programming Language :: Python :: 3.5
Classifier: Programming Language :: Python :: 3.6
Classifier: Topic :: Internet
Classifier: Topic :: Software Development :: Libraries
Classifier: Topic :: Software Development :: Libraries :: Python Modules
Classifier: Topic :: Utilities
Requires-Dist: aiohttp (>=2.2.5)
Requires-Dist: async-timeout (>=2.0.1)
Requires-Dist: attrs (>=17.4.0)
Requires-Dist: chardet (>=3.0.4)
Requires-Dist: diskcache (>=3.0.1)
Requires-Dist: idna (>=2.5)
Requires-Dist: idna-ssl (>=1.0.1)
Requires-Dist: multidict (>=4.1.0)
Requires-Dist: websockets (>=4.0.1)
Requires-Dist: yarl (>=1.1.1)
Requires-Dist: python-dateutil (>=0.1)
